{
  "version": "7",
  "dialect": "sqlite",
  "entries": [
    {
      "idx": 0,
      "version": "6",
      "when": 1753025414579,
      "tag": "0000_quick_scourge",
      "breakpoints": true
    },
    {
      "idx": 1,
      "version": "6",
      "when": 1753026308581,
      "tag": "0001_puzzling_iron_patriot",
      "breakpoints": true
    },
    {
      "idx": 2,
      "version": "6",
      "when": 1753026408227,
      "tag": "0002_melodic_daredevil",
      "breakpoints": true
    },
    {
      "idx": 3,
      "version": "6",
      "when": 1753026932731,
      "tag": "0003_shocking_fenris",
      "breakpoints": true
    }
  ]
}